yue_normalizer/__init__.py
yue_normalizer/chinese_normalizer.py
yue_normalizer/py.typed
yue_normalizer/tools.py
yue_normalizer/normalizer/__init__.py
yue_normalizer/normalizer/data_utils.py
yue_normalizer/normalizer/english_abbreviations.py
yue_normalizer/normalizer/eval_utils.py
yue_normalizer/normalizer/normalizer.py
yue_normalizer-0.1.1.dist-info/METADATA
yue_normalizer-0.1.1.dist-info/WHEEL
yue_normalizer-0.1.1.dist-info/RECORD
